carbon_registry_indexer/__init__.py
carbon_registry_indexer/common/__init__.py
carbon_registry_indexer/common/project_developers.py
carbon_registry_indexer/integrations/__init__.py
carbon_registry_indexer/integrations/constants.py
carbon_registry_indexer/integrations/sync_acr.py
carbon_registry_indexer/integrations/sync_art.py
carbon_registry_indexer/integrations/sync_cadt.py
carbon_registry_indexer/integrations/sync_car.py
carbon_registry_indexer/integrations/sync_gs.py
carbon_registry_indexer/integrations/sync_puro.py
carbon_registry_indexer/integrations/utils.py
carbon_registry_indexer/models/__init__.py
carbon_registry_indexer/models/enums.py
carbon_registry_indexer/models/target.py
carbon_registry_indexer/preprocessing/__init__.py
carbon_registry_indexer/preprocessing/preprocess_acr.py
carbon_registry_indexer/preprocessing/preprocess_art.py
carbon_registry_indexer/preprocessing/preprocess_cadt.py
carbon_registry_indexer/preprocessing/preprocess_car.py
carbon_registry_indexer/preprocessing/preprocess_gs.py
carbon_registry_indexer/preprocessing/preprocess_puro.py
carbon_registry_indexer-0.1.59.dist-info/LICENSE
carbon_registry_indexer-0.1.59.dist-info/METADATA
carbon_registry_indexer-0.1.59.dist-info/WHEEL
carbon_registry_indexer-0.1.59.dist-info/top_level.txt
carbon_registry_indexer-0.1.59.dist-info/RECORD
