Metadata-Version: 2.1
Name: carbon-registry-indexer
Version: 0.1.59
Summary: A Python library designed to streamline the aggregation of carbon data from multiple registries, each with its own data format, into a unified schema in CSV/Parquet formats.
Home-page: https://github.com/CarbonMarketsHQ/Carbon-Registry-Indexer
Download-URL: https://github.com/CarbonMarketsHQ/Carbon-Registry-Indexer/archive/refs/tags/v_0.1.7.tar.gz
Author: Gautam P
Author-email: gautam@carbonmarketshq.com
License: MIT
Classifier: Development Status :: 3 - Alpha
Classifier: Intended Audience :: Developers
Classifier: Topic :: Software Development :: Build Tools
Classifier: License :: OSI Approved :: MIT License
Classifier: Programming Language :: Python :: 3.11
License-File: LICENSE
Requires-Dist: sqlalchemy
Requires-Dist: pandas
Requires-Dist: openpyxl
Requires-Dist: strawberry-graphql
Requires-Dist: azure-storage-blob
